angeltools/ImageTool.py
angeltools/MathTool.py
angeltools/Slavers.py
angeltools/StrTool.py
angeltools/SysTool.py
angeltools/TimeTool.py
angeltools/__init__.py
angeltools/commands.py
angeltools/Db/__init__.py
angeltools/Db/redis_connector.py
angeltools/fdfs/__init__.py
angeltools/fdfs/fdfs_operator.py
angeltools/fdfs/fdfs_client/__init__.py
angeltools/fdfs/fdfs_client/client.py
angeltools/fdfs/fdfs_client/connection.py
angeltools/fdfs/fdfs_client/exceptions.py
angeltools/fdfs/fdfs_client/fdfs_protol.py
angeltools/fdfs/fdfs_client/fdfs_test.py
angeltools/fdfs/fdfs_client/storage_client.py
angeltools/fdfs/fdfs_client/tracker_client.py
angeltools/fdfs/fdfs_client/utils.py
angeltools-0.3.7.dist-info/LICENSE
angeltools-0.3.7.dist-info/METADATA
angeltools-0.3.7.dist-info/WHEEL
angeltools-0.3.7.dist-info/entry_points.txt
angeltools-0.3.7.dist-info/top_level.txt
angeltools-0.3.7.dist-info/RECORD
