Metadata-Version: 2.1
Name: angeltools
Version: 0.3.7
Summary: personal python small tools collection
Home-page: https://github.com/ga1008/angeltools
Author: Guardian
Author-email: zhling2012@live.com
Maintainer: Guardian
Maintainer-email: zhling2012@live.com
Classifier: Programming Language :: Python :: 3
Classifier: License :: OSI Approved :: MIT License
Classifier: Operating System :: OS Independent
License-File: LICENSE
Requires-Dist: setuptools
Requires-Dist: tqdm
Requires-Dist: numpy
Requires-Dist: psutil
Requires-Dist: redis
Requires-Dist: scrapy
Requires-Dist: requests
Requires-Dist: pygame
Requires-Dist: pillow
Requires-Dist: pypinyin
Requires-Dist: basecolors
